infra/__init__.py
infra/cli.py
infra/config.py
infraai-0.2.3.dist-info/METADATA
infraai-0.2.3.dist-info/WHEEL
infraai-0.2.3.dist-info/entry_points.txt
infraai-0.2.3.dist-info/licenses/LICENSE
infraai-0.2.3.dist-info/RECORD
