Metadata-Version: 2.3
Name: infraai
Version: 0.2.3
Summary: A minimalistic AI assistant designed to assist infrastructure engineers and developers with various tasks related to infrastructure management, deployment, and development.
Project-URL: Homepage, https://github.com/sumant1122/InfraAI
Project-URL: Issues, https://github.com/sumant1122/InfraAI/issues
Author-email: Sumant Sogikar <sumant1122@gmail.com>
License-File: LICENSE
Classifier: Development Status :: 4 - Beta
Classifier: Intended Audience :: Developers
Classifier: License :: OSI Approved :: MIT License
Classifier: Operating System :: OS Independent
Classifier: Programming Language :: Python :: 3
Classifier: Topic :: Scientific/Engineering :: Artificial Intelligence
Classifier: Topic :: Software Development :: Libraries :: Python Modules
Requires-Python: >=3.9
Requires-Dist: configparser
Requires-Dist: distro
Requires-Dist: google-generativeai
Requires-Dist: rich
